aqueue/__init__.py
aqueue/display.py
aqueue/processing.py
aqueue/queue.py
aqueue-0.9.3.dist-info/LICENSE.txt
aqueue-0.9.3.dist-info/METADATA
aqueue-0.9.3.dist-info/WHEEL
aqueue-0.9.3.dist-info/RECORD
