Metadata-Version: 2.3
Name: aqueue
Version: 0.9.3
Summary: An async task queue with live progress display
Home-page: https://t-mart.github.io/aqueue/
License: MIT
Keywords: queue,async,task
Author: Tim Martin
Author-email: tim@timmart.in
Requires-Python: >=3.12,<4.0
Classifier: Development Status :: 4 - Beta
Classifier: Environment :: Console
Classifier: Framework :: AnyIO
Classifier: Intended Audience :: Developers
Classifier: License :: OSI Approved :: MIT License
Classifier: Natural Language :: English
Classifier: Operating System :: OS Independent
Classifier: Programming Language :: Python
Classifier: Programming Language :: Python :: 3
Classifier: Programming Language :: Python :: 3.12
Classifier: Programming Language :: Python :: 3.13
Classifier: Programming Language :: Python :: 3.10
Classifier: Topic :: Software Development :: Libraries :: Python Modules
Requires-Dist: anyio (>=4,<5)
Requires-Dist: attrs (>=24,<25)
Requires-Dist: rich (>=13,<14)
Requires-Dist: sortedcontainers (>=2,<3)
Project-URL: Documentation, https://t-mart.github.io/aqueue/
Project-URL: Repository, https://github.com/t-mart/aqueue
